{"ORG" : "Kingston Technology", "GPE" : []}
{"ORG" : "Emcor", "GPE" : []}
{"ORG" : "Wausau Paper", "GPE" : []}
{"ORG" : "NACCO Industries", "GPE" : []}
{"ORG" : "Ford Motor Company", "GPE" : []}
{"ORG" : "LeapFrog Enterprises", "GPE" : []}
{"ORG" : "Cummins", "GPE" : []}
{"ORG" : "Teradyne", "GPE" : []}
{"ORG" : "AnaSpec", "GPE" : []}
{"ORG" : "Chipotle Mexican Grill", "GPE" : []}
{"ORG" : "Avon Products", "GPE" : []}
{"ORG" : "BMC Software", "GPE" : []}
{"ORG" : "Six Flags", "GPE" : []}
{"ORG" : "CoolTouch Monitors", "GPE" : []}
{"ORG" : "CEB Inc.", "GPE" : []}
{"ORG" : "Qualcomm", "GPE" : []}
{"ORG" : "Aetna", "GPE" : []}
{"ORG" : "Andronico's", "GPE" : []}
{"ORG" : "Altec Lansing", "GPE" : []}
{"ORG" : "Activision", "GPE" : []}
{"ORG" : "Lucas Oil", "GPE" : []}
{"ORG" : "LabCorp", "GPE" : []}
{"ORG" : "General Mills", "GPE" : []}
{"ORG" : "Cantor Fitzgerald", "GPE" : []}
{"ORG" : "KeyBank", "GPE" : []}
{"ORG" : "Leggett &amp; Platt", "GPE" : []}
{"ORG" : "Louisiana-Pacific", "GPE" : []}
{"ORG" : "Focus Brands", "GPE" : []}
{"ORG" : "Big Boy Restaurants", "GPE" : []}
{"ORG" : "Magnavox", "GPE" : []}
{"ORG" : "Ashley Furniture Industries", "GPE" : []}
{"ORG" : "Mercury Marine", "GPE" : []}
{"ORG" : "W. R. Grace and Company", "GPE" : []}
{"ORG" : "Esterline", "GPE" : []}
{"ORG" : "T. Rowe Price", "GPE" : []}
{"ORG" : "Lennox International", "GPE" : []}
{"ORG" : "Owens-Illinois", "GPE" : []}
{"ORG" : "Avaya", "GPE" : []}
{"ORG" : "Anchor Bay Entertainment", "GPE" : []}
{"ORG" : "Anixter", "GPE" : []}
{"ORG" : "Interplay Entertainment", "GPE" : []}
{"ORG" : "Diebold", "GPE" : []}
{"ORG" : "Charter Arms", "GPE" : []}
{"ORG" : "Alaska Air Group", "GPE" : []}
{"ORG" : "Georgia-Pacific", "GPE" : []}
{"ORG" : "Occidental Petroleum", "GPE" : []}
{"ORG" : "Dollar Tree", "GPE" : []}
{"ORG" : "Biomet", "GPE" : []}
{"ORG" : "American Axle", "GPE" : []}
{"ORG" : "Denbury Resources", "GPE" : []}
{"ORG" : "Entergy", "GPE" : []}
{"ORG" : "Activision Blizzard", "GPE" : []}
{"ORG" : "Kahr Arms", "GPE" : []}
{"ORG" : "Bose Corporation", "GPE" : []}
{"ORG" : "Teradata", "GPE" : []}
{"ORG" : "Planet Hollywood", "GPE" : []}
{"ORG" : "Six Flags", "GPE" : []}
{"ORG" : "Dollar Tree", "GPE" : []}
{"ORG" : "Alexion Pharmaceuticals", "GPE" : []}
{"ORG" : "BrightPoint", "GPE" : []}
{"ORG" : "TransDigm Group", "GPE" : []}
{"ORG" : "United Country Real Estate", "GPE" : []}
{"ORG" : "Dean Foods", "GPE" : []}
{"ORG" : "Plains All American Pipeline", "GPE" : []}
{"ORG" : "DynCorp", "GPE" : []}
{"ORG" : "American Apparel", "GPE" : []}
{"ORG" : "Ashland Inc.", "GPE" : []}
{"ORG" : "Russell Investments", "GPE" : []}
{"ORG" : "Lehman Brothers", "GPE" : []}
{"ORG" : "Gordon Food Service", "GPE" : []}
{"ORG" : "Columbia Sussex", "GPE" : []}
{"ORG" : "Omnicare", "GPE" : []}
{"ORG" : "Interstate Batteries", "GPE" : []}
{"ORG" : "Adaptec", "GPE" : []}
{"ORG" : "Hewlett Packard Enterprise", "GPE" : []}
{"ORG" : "Ceridian", "GPE" : []}
{"ORG" : "Owens Corning", "GPE" : []}
{"ORG" : "Nordstrom", "GPE" : []}
{"ORG" : "Erie Insurance Group", "GPE" : []}
{"ORG" : "Airgas", "GPE" : []}
{"ORG" : "Ecolab", "GPE" : []}
{"ORG" : "MIG, Inc.", "GPE" : []}
{"ORG" : "Cumberland Farms", "GPE" : []}
{"ORG" : "DaVita", "GPE" : []}
{"ORG" : "Dole Food Company", "GPE" : []}
{"ORG" : "Papa John's Pizza", "GPE" : []}
{"ORG" : "Paramount Pictures", "GPE" : []}
{"ORG" : "Traxxas", "GPE" : []}
{"ORG" : "Chugach Alaska Corporation", "GPE" : []}
{"ORG" : "Babcock &amp; Wilcox", "GPE" : []}
{"ORG" : "FedEx", "GPE" : []}
{"ORG" : "Wabtec Corporation", "GPE" : []}
{"ORG" : "PetSmart", "GPE" : []}
{"ORG" : "Altra Industrial Motion", "GPE" : []}
{"ORG" : "Nuance Communications", "GPE" : []}
{"ORG" : "Sbarro", "GPE" : []}
{"ORG" : "Pall Corporation", "GPE" : []}
{"ORG" : "Huntington Ingalls Industries", "GPE" : []}
{"ORG" : "Eli Lilly and Company", "GPE" : []}
{"ORG" : "Consol Energy", "GPE" : []}
